gradio_model4dgs/__init__.py
gradio_model4dgs/model4dgs.py
gradio_model4dgs/model4dgs.pyi
gradio_model4dgs/templates/component/index.js
gradio_model4dgs/templates/component/style.css
gradio_model4dgs/templates/example/index.js
gradio_model4dgs/templates/example/style.css
gradio_model4dgs-0.0.5.dist-info/METADATA
gradio_model4dgs-0.0.5.dist-info/WHEEL
gradio_model4dgs-0.0.5.dist-info/RECORD
